{
  "match": "Argentina vs Egypt — FIFA World Cup 2026, Round of 16",
  "venue": "Mercedes-Benz Stadium, Atlanta",
  "date": "2026-07-07",
  "score": "3-2",
  "note": "Goal/penalty minutes are real (per ESPN/Sky Sports match reports). Other threat events are reconstructed from match reports and calibrated against Flashscore's independent momentum graphic for this match (Argentina dominated territory; Egypt scored on counters at 15' and 67') - not official event data.",
  "teams": {"home": "ARG", "away": "EGY"},
  "title": "MATCH MOMENTUM  —  ARGENTINA 3–2 EGYPT",
  "colors": {"home": "#6CACE4", "away": "#CE1126"},
  "footer": "World Cup 2026 · Round of 16 · Mercedes-Benz Stadium, Atlanta · goal minutes real, threat events reconstructed from match reports",
  "events": [
    {"minute": 5,  "team": "ARG", "type": "pressure", "weight": 0.5},
    {"minute": 9,  "team": "EGY", "type": "chance",   "weight": 0.6},
    {"minute": 12, "team": "ARG", "type": "shot",     "weight": 0.8},
    {"minute": 14, "team": "EGY", "type": "pressure", "weight": 0.8},
    {"minute": 15, "team": "EGY", "type": "goal",     "weight": 1.8, "label": "Ibrahim 15'"},
    {"minute": 18, "team": "EGY", "type": "pressure", "weight": 0.6},
    {"minute": 20, "team": "ARG", "type": "pressure", "weight": 0.7},
    {"minute": 21, "team": "ARG", "type": "penalty_missed", "weight": 1.2, "label": "Messi pen saved 21'"},
    {"minute": 28, "team": "ARG", "type": "shot",     "weight": 0.9},
    {"minute": 31, "team": "ARG", "type": "chance",   "weight": 0.7},
    {"minute": 35, "team": "ARG", "type": "pressure", "weight": 0.6},
    {"minute": 41, "team": "ARG", "type": "shot",     "weight": 0.8},
    {"minute": 44, "team": "ARG", "type": "chance",   "weight": 0.9},
    {"minute": 45, "team": "EGY", "type": "shot",     "weight": 0.5},

    {"minute": 48, "team": "ARG", "type": "shot",     "weight": 0.7},
    {"minute": 51, "team": "EGY", "type": "chance",   "weight": 0.6},
    {"minute": 54, "team": "ARG", "type": "pressure", "weight": 0.6},
    {"minute": 58, "team": "ARG", "type": "shot",     "weight": 0.6},
    {"minute": 62, "team": "ARG", "type": "pressure", "weight": 0.5},
    {"minute": 66, "team": "EGY", "type": "pressure", "weight": 0.8},
    {"minute": 67, "team": "EGY", "type": "goal",     "weight": 1.8, "label": "Zico 67'"},
    {"minute": 71, "team": "ARG", "type": "shot",     "weight": 0.7},
    {"minute": 74, "team": "ARG", "type": "shot",     "weight": 0.9},
    {"minute": 76, "team": "ARG", "type": "pressure", "weight": 1.0},
    {"minute": 79, "team": "ARG", "type": "goal",     "weight": 1.8, "label": "Romero 79'"},
    {"minute": 81, "team": "ARG", "type": "pressure", "weight": 1.0},
    {"minute": 84, "team": "ARG", "type": "goal",     "weight": 1.8, "label": "Messi 84'"},
    {"minute": 87, "team": "ARG", "type": "chance",   "weight": 0.9},
    {"minute": 90, "team": "ARG", "type": "pressure", "weight": 0.9},
    {"minute": 92, "team": "ARG", "type": "goal",     "weight": 2.0, "label": "Enzo 90+2'"}
  ]
}
